Metadata-Version: 2.4
Name: PyPlaque
Version: 0.2.4
Summary: Python package for virus plaque analysis based on Plaque2.0
Home-page: https://github.com/plaque2/PyPlaque
Download-URL: https://github.com/plaque2/PyPlaque/archive/v0.2.4.tar.gz
Author: Plaque2.0 Team, AILS Institute, CASUS HZDR
Author-email: ayakimovich@ails.institute, trinade96@gmail.com
License: GPLv3
Keywords: Virus,Plaque,Virology,Microscopy,Computer vision
Classifier: Development Status :: 3 - Alpha
Classifier: Intended Audience :: Science/Research
Classifier: Topic :: Scientific/Engineering :: Bio-Informatics
Classifier: License :: OSI Approved :: GNU General Public License v3 (GPLv3)
Classifier: Programming Language :: Python :: 3.9
Classifier: Programming Language :: Python :: 3.10
Classifier: Programming Language :: Python :: 3.11
Classifier: Programming Language :: Python :: 3.12
Requires-Python: >=3.9, <=3.12
License-File: LICENSE
Requires-Dist: scikit-image>=0.24.0
Requires-Dist: numpy>=2.0.0
Requires-Dist: matplotlib>=3.7.0
Requires-Dist: opencv-python>=4.10.0.84
Requires-Dist: Pillow>=10.3.0
Requires-Dist: pandas>=1.5.3
Requires-Dist: scipy>=1.13.1
Requires-Dist: scikit-learn>=1.5.0
Requires-Dist: seaborn==0.12.2
Requires-Dist: tqdm>=4.66.4
Requires-Dist: tifffile>=2023.2.28
Provides-Extra: test
Requires-Dist: pytest>=8.1.1; extra == "test"
Dynamic: author
Dynamic: author-email
Dynamic: classifier
Dynamic: description
Dynamic: description-content-type
Dynamic: download-url
Dynamic: home-page
Dynamic: keywords
Dynamic: license
Dynamic: license-file
Dynamic: provides-extra
Dynamic: requires-dist
Dynamic: requires-python
Dynamic: summary
